efficientv2_unet/__init__.py
efficientv2_unet/__main__.py
efficientv2_unet/cli.py
efficientv2_unet/version.py
efficientv2_unet/model/__init__.py
efficientv2_unet/model/efficientv2_unet.py
efficientv2_unet/model/metrics.py
efficientv2_unet/model/predict.py
efficientv2_unet/utils/__init__.py
efficientv2_unet/utils/data_generation.py
efficientv2_unet/utils/tile_utils.py
efficientv2_unet/utils/visualize.py
efficientv2_unet-0.0.5.dist-info/METADATA
efficientv2_unet-0.0.5.dist-info/WHEEL
efficientv2_unet-0.0.5.dist-info/entry_points.txt
efficientv2_unet-0.0.5.dist-info/licenses/LICENSE
efficientv2_unet-0.0.5.dist-info/RECORD
