Metadata-Version: 2.3
Name: efficientv2-unet
Version: 0.0.5
Summary: A U-Net implementation of the EfficientNetV2.
Project-URL: homepage, https://github.com/DBM-MCF/efficientv2-unet
Project-URL: repository, https://github.com/DBM-MCF/efficientv2-unet
Author-email: Loïc Sauteur <loic.sauteur@unibas.ch>
License: BSD-3-Clause
License-File: LICENSE
Classifier: Development Status :: 3 - Alpha
Classifier: License :: OSI Approved :: BSD License
Classifier: Programming Language :: Python :: 3
Classifier: Programming Language :: Python :: 3.9
Classifier: Programming Language :: Python :: 3.10
Classifier: Typing :: Typed
Requires-Python: <3.11,>=3.9
Requires-Dist: albumentations<=1.4.0
Requires-Dist: keras==2.10.0; platform_system == 'Windows'
Requires-Dist: matplotlib==3.9.2
Requires-Dist: notebook==7.2.2
Requires-Dist: numpy<2.0,>1.26
Requires-Dist: opencv-python==4.10.0.84
Requires-Dist: pandas==2.2
Requires-Dist: scikit-image==0.24.0
Requires-Dist: tensorflow-macos==2.15.0; platform_system == 'Darwin' and platform_machine == 'arm64'
Requires-Dist: tensorflow-metal==1.1.0; platform_system == 'Darwin' and platform_machine == 'arm64'
Requires-Dist: tensorflow==2.10.1; platform_system == 'Windows'
Requires-Dist: tensorflow==2.15.0; platform_system == 'Darwin' and platform_machine != 'arm64'
Requires-Dist: tensorflow[and-cuda]==2.15.*; platform_system == 'Linux'
Requires-Dist: tifffile==2024.8.30
Provides-Extra: dev
Requires-Dist: ipython; extra == 'dev'
Requires-Dist: mypy; extra == 'dev'
Requires-Dist: pdbpp; extra == 'dev'
Requires-Dist: pre-commit; extra == 'dev'
Requires-Dist: rich; extra == 'dev'
Requires-Dist: ruff; extra == 'dev'
Provides-Extra: test
Requires-Dist: pytest; extra == 'test'
Requires-Dist: pytest-cov; extra == 'test'
